decorrelation/__init__.py
decorrelation/_modidx.py
decorrelation/co.py
decorrelation/pc.py
decorrelation/pl.py
decorrelation/plot.py
decorrelation/ps.py
decorrelation/shp.py
decorrelation/cli/__init__.py
decorrelation/cli/co.py
decorrelation/cli/load.py
decorrelation/cli/math.py
decorrelation/cli/pc.py
decorrelation/cli/pl.py
decorrelation/cli/ps.py
decorrelation/cli/shp.py
decorrelation/cli/utils/__init__.py
decorrelation/cli/utils/appconfig.py
decorrelation/cli/utils/chunk_size.py
decorrelation/cli/utils/dask.py
decorrelation/cli/utils/logging.py
decorrelation/cli/utils/transform.py
decorrelation-0.5.1.dist-info/LICENSE
decorrelation-0.5.1.dist-info/METADATA
decorrelation-0.5.1.dist-info/WHEEL
decorrelation-0.5.1.dist-info/entry_points.txt
decorrelation-0.5.1.dist-info/top_level.txt
decorrelation-0.5.1.dist-info/RECORD
