Metadata-Version: 2.1
Name: decorrelation
Version: 0.5.1
Summary: An InSAR postprocessing tool
Home-page: https://github.com/kanglcn/decorrelation
Author: kanglcn
Author-email: kanglcn@gmail.com
License: GNU General Public License v3.0 only
Keywords: InSAR PS DS CUDA Deep-learning
Classifier: Development Status :: 4 - Beta
Classifier: Intended Audience :: Developers
Classifier: Natural Language :: English
Classifier: Programming Language :: Python :: 3.10
Classifier: License :: OSI Approved :: GNU General Public License v3 (GPLv3)
Requires-Python: >=3.10
License-File: LICENSE
Requires-Dist: numpy
Requires-Dist: scipy
Requires-Dist: matplotlib
Requires-Dist: zarr
Requires-Dist: dask
Requires-Dist: colorcet
Requires-Dist: fastcore
Requires-Dist: toml
Requires-Dist: numba
Requires-Dist: numexpr
Requires-Dist: holoviews
Requires-Dist: datashader
Requires-Dist: pyproj >=3.0
Provides-Extra: dev
Requires-Dist: nbdev ; extra == 'dev'
Requires-Dist: pre-commit ; extra == 'dev'
